<?xml version="1.0" encoding="utf-8" ?><dwsync><file name="Crystal_Clear_write.gif" server="C:/xampp/htdocs/johnsonsInn/" local="129915029270948432" remote="129915029270000000" Dst="0" /><file name="Crystal_Clear_file.gif" server="C:/xampp/htdocs/johnsonsInn/" local="129915029268498292" remote="129915029260000000" Dst="0" /><file name="Crystal_Clear_files.gif" server="C:/xampp/htdocs/johnsonsInn/" local="129915029268858312" remote="129915029260000000" Dst="0" /><file name="Crystal_Clear_calendar.gif" server="C:/xampp/htdocs/johnsonsInn/" local="129915029268058267" remote="129915029260000000" Dst="0" /><file name="Crystal_Clear_user.gif" server="C:/xampp/htdocs/johnsonsInn/" local="129915029270538408" remote="129915029270000000" Dst="0" /><file name="Crystal_Clear_stats.gif" server="C:/xampp/htdocs/johnsonsInn/" local="129915029270048380" remote="129915029270000000" Dst="0" /><file name="Crystal_Clear_settings.gif" server="C:/xampp/htdocs/johnsonsInn/" local="129915029269638357" remote="129915029260000000" Dst="0" /><file name="plus-small.gif" server="C:/xampp/htdocs/johnsonsInn/" local="129915030041622512" remote="129915030040000000" Dst="0" /><file name="logo.gif" server="C:/xampp/htdocs/johnsonsInn/" local="129915029896974238" remote="129915029890000000" Dst="0" /><file name="header-bg.jpg" server="C:/xampp/htdocs/johnsonsInn/" local="129915029462969415" remote="129915029460000000" Dst="0" /><file name="tab-left.gif" server="C:/xampp/htdocs/johnsonsInn/" local="129915030438065187" remote="129915030430000000" Dst="0" /><file name="tab-right.gif" server="C:/xampp/htdocs/johnsonsInn/" local="129915030438585217" remote="129915030430000000" Dst="0" /><file name="tab-active-left.gif" server="C:/xampp/htdocs/johnsonsInn/" local="129915030437075130" remote="129915030430000000" Dst="0" /><file name="tab-active-right.gif" server="C:/xampp/htdocs/johnsonsInn/" local="129915030437565158" remote="129915030430000000" Dst="0" /><file name="icon-logout.gif" server="C:/xampp/htdocs/johnsonsInn/" local="129915029463579450" remote="129915029460000000" Dst="0" /><file name="submenu-bg.gif" server="C:/xampp/htdocs/johnsonsInn/" local="129915030243034032" remote="129915030240000000" Dst="0" /><file name="module-body-left-bg.gif" server="C:/xampp/htdocs/johnsonsInn/" local="129915030036672229" remote="129915030030000000" Dst="0" /><file name="module-body-right-bg.gif" server="C:/xampp/htdocs/johnsonsInn/" local="129915030037172257" remote="129915030030000000" Dst="0" /><file name="module-header-left-bg.gif" server="C:/xampp/htdocs/johnsonsInn/" local="129915030037712288" remote="129915030030000000" Dst="0" /><file name="module-header-right-bg.gif" server="C:/xampp/htdocs/johnsonsInn/" local="129915030038352325" remote="129915030030000000" Dst="0" /><file name="button-right-bg-m.gif" server="C:/xampp/htdocs/johnsonsInn/" local="129915029266648186" remote="129915029260000000" Dst="0" /><file name="button-left-bg-m.gif" server="C:/xampp/htdocs/johnsonsInn/" local="129915029265808138" remote="129915029260000000" Dst="0" /><file name="button-right-bg.gif" server="C:/xampp/htdocs/johnsonsInn/" local="129915029266958204" remote="129915029260000000" Dst="0" /><file name="button-left-bg.gif" server="C:/xampp/htdocs/johnsonsInn/" local="129915029266078153" remote="129915029260000000" Dst="0" /><file name="input-bg.gif" server="C:/xampp/htdocs/johnsonsInn/" local="129915029661670780" remote="129915029660000000" Dst="0" /><file name="input-bg-focus.gif" server="C:/xampp/htdocs/johnsonsInn/" local="129915029661110748" remote="129915029660000000" Dst="0" /><file name="submit-green-bg.gif" server="C:/xampp/htdocs/johnsonsInn/" local="129915030436275085" remote="129915030430000000" Dst="0" /><file name="submit-green-bg-hover.gif" server="C:/xampp/htdocs/johnsonsInn/" local="129915030435755055" remote="129915030430000000" Dst="0" /><file name="submit-gray-bg.gif" server="C:/xampp/htdocs/johnsonsInn/" local="129915030435235025" remote="129915030430000000" Dst="0" /><file name="submit-gray-bg-hover.gif" server="C:/xampp/htdocs/johnsonsInn/" local="129915030434694994" remote="129915030430000000" Dst="0" /><file name="tick-on-white.gif" server="C:/xampp/htdocs/johnsonsInn/" local="129915030525260174" remote="129915030520000000" Dst="0" /><file name="cross-on-white.gif" server="C:/xampp/htdocs/johnsonsInn/" local="129915029267308224" remote="129915029260000000" Dst="0" /><file name="notification-tick.gif" server="C:/xampp/htdocs/johnsonsInn/" local="129915030040582452" remote="129915030040000000" Dst="0" /><file name="notification-information.gif" server="C:/xampp/htdocs/johnsonsInn/" local="129915030039392384" remote="129915030030000000" Dst="0" /><file name="notification-exclamation.gif" server="C:/xampp/htdocs/johnsonsInn/" local="129915030038892356" remote="129915030030000000" Dst="0" /><file name="notification-slash.gif" server="C:/xampp/htdocs/johnsonsInn/" local="129915030039942416" remote="129915030030000000" Dst="0" /><file name="indicator-bg.gif" server="C:/xampp/htdocs/johnsonsInn/" local="129915029659400650" remote="129915029650000000" Dst="0" /><file name="indicator-green-to-red.gif" server="C:/xampp/htdocs/johnsonsInn/" local="129915029659970683" remote="129915029650000000" Dst="0" /><file name="indicator-red-to-green.gif" server="C:/xampp/htdocs/johnsonsInn/" local="129915029660500713" remote="129915029660000000" Dst="0" /><file name="cross-small.gif" server="C:/xampp/htdocs/johnsonsInn/" local="129915029267658244" remote="129915029260000000" Dst="0" /><file name="tick-small.gif" server="C:/xampp/htdocs/johnsonsInn/" local="129915030525760203" remote="129915030520000000" Dst="0" /><file name="user.gif" server="C:/xampp/htdocs/johnsonsInn/" local="129915030527140282" remote="129915030520000000" Dst="0" /><file name="user-female.gif" server="C:/xampp/htdocs/johnsonsInn/" local="129915030526630253" remote="129915030520000000" Dst="0" /><file name="arrow-curve-180-left.gif" server="C:/xampp/htdocs/johnsonsInn/" local="129915029263207989" remote="129915029260000000" Dst="0" /><file name="arrow-curve-000-left.gif" server="C:/xampp/htdocs/johnsonsInn/" local="129915029262997977" remote="129915029260000000" Dst="0" /><file name="Crystal_Project_mail_open.gif" server="C:/xampp/htdocs/johnsonsInn/" local="129915029271388457" remote="129915029270000000" Dst="0" /><file name="Crystal_Clear_locked.gif" server="C:/xampp/htdocs/johnsonsInn/" local="129915029269248335" remote="129915029260000000" Dst="0" /><file name="dashboard-module.gif" server="C:/xampp/htdocs/johnsonsInn/" local="129915029271858484" remote="129915029270000000" Dst="0" /><file name="jquery.wysiwyg.gif" server="C:/xampp/htdocs/johnsonsInn/" local="129915029896424207" remote="129915029890000000" Dst="0" /><file name="tick-circle.gif" server="C:/xampp/htdocs/johnsonsInn/" local="129915030524720143" remote="129915030520000000" Dst="0" /><file name="pencil.gif" server="C:/xampp/htdocs/johnsonsInn/" local="129915030041112483" remote="129915030040000000" Dst="0" /><file name="balloon.gif" server="C:/xampp/htdocs/johnsonsInn/" local="129915029265008092" remote="129915029260000000" Dst="0" /><file name="minus-circle.gif" server="C:/xampp/htdocs/johnsonsInn/" local="129915030036102196" remote="129915030030000000" Dst="0" /><file name="bin.gif" server="C:/xampp/htdocs/johnsonsInn/" local="129915029265528122" remote="129915029260000000" Dst="0" /><file name="arrow-stop-180.gif" server="C:/xampp/htdocs/johnsonsInn/" local="129915029263948031" remote="129915029260000000" Dst="0" /><file name="arrow-180.gif" server="C:/xampp/htdocs/johnsonsInn/" local="129915029262827967" remote="129915029260000000" Dst="0" /><file name="arrow.gif" server="C:/xampp/htdocs/johnsonsInn/" local="129915029264528065" remote="129915029260000000" Dst="0" /><file name="arrow-stop.gif" server="C:/xampp/htdocs/johnsonsInn/" local="129915029264288051" remote="129915029260000000" Dst="0" /><file name="arrow-stop-180-small.gif" server="C:/xampp/htdocs/johnsonsInn/" local="129915029263608012" remote="129915029260000000" Dst="0" /><file name="arrow-180-small.gif" server="C:/xampp/htdocs/johnsonsInn/" local="129915029262647957" remote="129915029260000000" Dst="0" /><file name="arrow-000-small.gif" server="C:/xampp/htdocs/johnsonsInn/" local="129915029262467947" remote="129915029260000000" Dst="0" /><file name="arrow-stop-000-small.gif" server="C:/xampp/htdocs/johnsonsInn/" local="129915029263398000" remote="129915029260000000" Dst="0" /><file name="dollar_coin.png" server="C:/xampp/htdocs/johnsonsInn/" local="129622210280000000" remote="129622210280000000" Dst="0" /><file name="coffee.png" server="C:/xampp/htdocs/johnsonsInn/" local="129076219600000000" remote="129076219600000000" Dst="0" /><file name="business_male_female_users.png" server="C:/xampp/htdocs/johnsonsInn/" local="128940422080000000" remote="128940422080000000" Dst="0" /><file name="female_user.png" server="C:/xampp/htdocs/johnsonsInn/" local="128940421960000000" remote="128940421960000000" Dst="0" /><file name="icon-logout.gif" server="C:/xampp/htdocs/firmVote0.2/" local="129915281480000000" remote="129915281480000000" Dst="2" /><file name="header-bg.jpg" server="C:/xampp/htdocs/firmVote0.2/" local="130086708628693998" remote="130086708620000000" Dst="2" /><file name="logo.gif" server="C:/xampp/htdocs/firmVote0.2/" local="130089851762063603" remote="130089851760000000" Dst="2" /><file name="submenu-bg.gif" server="C:/xampp/htdocs/firmVote0.2/" local="129915282260000000" remote="129915282260000000" Dst="2" /><file name="tab-left.gif" server="C:/xampp/htdocs/firmVote0.2/" local="129915282440000000" remote="129915282440000000" Dst="2" /><file name="tab-right.gif" server="C:/xampp/htdocs/firmVote0.2/" local="129915282440000000" remote="129915282440000000" Dst="2" /><file name="tab-active-left.gif" server="C:/xampp/htdocs/firmVote0.2/" local="129915282440000000" remote="129915282440000000" Dst="2" /><file name="tab-active-right.gif" server="C:/xampp/htdocs/firmVote0.2/" local="129915282440000000" remote="129915282440000000" Dst="2" /><file name="module-body-left-bg.gif" server="C:/xampp/htdocs/firmVote0.2/" local="129915282040000000" remote="129915282040000000" Dst="2" /><file name="module-body-right-bg.gif" server="C:/xampp/htdocs/firmVote0.2/" local="129915282040000000" remote="129915282040000000" Dst="2" /><file name="module-header-left-bg.gif" server="C:/xampp/htdocs/firmVote0.2/" local="129915282040000000" remote="129915282040000000" Dst="2" /><file name="module-header-right-bg.gif" server="C:/xampp/htdocs/firmVote0.2/" local="129915282040000000" remote="129915282040000000" Dst="2" /><file name="button-right-bg-m.gif" server="C:/xampp/htdocs/firmVote0.2/" local="129915281280000000" remote="129915281280000000" Dst="2" /><file name="button-left-bg-m.gif" server="C:/xampp/htdocs/firmVote0.2/" local="129915281280000000" remote="129915281280000000" Dst="2" /><file name="button-right-bg.gif" server="C:/xampp/htdocs/firmVote0.2/" local="129915281280000000" remote="129915281280000000" Dst="2" /><file name="button-left-bg.gif" server="C:/xampp/htdocs/firmVote0.2/" local="129915281280000000" remote="129915281280000000" Dst="2" /><file name="input-bg.gif" server="C:/xampp/htdocs/firmVote0.2/" local="129915281680000000" remote="129915281680000000" Dst="2" /><file name="input-bg-focus.gif" server="C:/xampp/htdocs/firmVote0.2/" local="129915281680000000" remote="129915281680000000" Dst="2" /><file name="submit-green-bg.gif" server="C:/xampp/htdocs/firmVote0.2/" local="129915282440000000" remote="129915282440000000" Dst="2" /><file name="submit-green-bg-hover.gif" server="C:/xampp/htdocs/firmVote0.2/" local="129915282440000000" remote="129915282440000000" Dst="2" /><file name="submit-gray-bg.gif" server="C:/xampp/htdocs/firmVote0.2/" local="129915282440000000" remote="129915282440000000" Dst="2" /><file name="submit-gray-bg-hover.gif" server="C:/xampp/htdocs/firmVote0.2/" local="129915282440000000" remote="129915282440000000" Dst="2" /><file name="tick-on-white.gif" server="C:/xampp/htdocs/firmVote0.2/" local="129915282540000000" remote="129915282540000000" Dst="2" /><file name="cross-on-white.gif" server="C:/xampp/htdocs/firmVote0.2/" local="129915281280000000" remote="129915281280000000" Dst="2" /><file name="notification-tick.gif" server="C:/xampp/htdocs/firmVote0.2/" local="129915282060000000" remote="129915282060000000" Dst="2" /><file name="notification-information.gif" server="C:/xampp/htdocs/firmVote0.2/" local="129915282040000000" remote="129915282040000000" Dst="2" /><file name="notification-exclamation.gif" server="C:/xampp/htdocs/firmVote0.2/" local="129915282040000000" remote="129915282040000000" Dst="2" /><file name="notification-slash.gif" server="C:/xampp/htdocs/firmVote0.2/" local="129915282040000000" remote="129915282040000000" Dst="2" /><file name="indicator-bg.gif" server="C:/xampp/htdocs/firmVote0.2/" local="129915281660000000" remote="129915281660000000" Dst="2" /><file name="indicator-green-to-red.gif" server="C:/xampp/htdocs/firmVote0.2/" local="129915281660000000" remote="129915281660000000" Dst="2" /><file name="indicator-red-to-green.gif" server="C:/xampp/htdocs/firmVote0.2/" local="129915281680000000" remote="129915281680000000" Dst="2" /><file name="cross-small.gif" server="C:/xampp/htdocs/firmVote0.2/" local="129915281280000000" remote="129915281280000000" Dst="2" /><file name="tick-small.gif" server="C:/xampp/htdocs/firmVote0.2/" local="129915282540000000" remote="129915282540000000" Dst="2" /><file name="user.gif" server="C:/xampp/htdocs/firmVote0.2/" local="129915282540000000" remote="129915282540000000" Dst="2" /><file name="user-female.gif" server="C:/xampp/htdocs/firmVote0.2/" local="129915282540000000" remote="129915282540000000" Dst="2" /><file name="arrow-curve-180-left.gif" server="C:/xampp/htdocs/firmVote0.2/" local="129915281280000000" remote="129915281280000000" Dst="2" /><file name="arrow-curve-000-left.gif" server="C:/xampp/htdocs/firmVote0.2/" local="129915281280000000" remote="129915281280000000" Dst="2" /><file name="Crystal_Project_mail_open.gif" server="C:/xampp/htdocs/firmVote0.2/" local="129915281280000000" remote="129915281280000000" Dst="2" /><file name="Crystal_Clear_locked.gif" server="C:/xampp/htdocs/firmVote0.2/" local="129915281280000000" remote="129915281280000000" Dst="2" /><file name="dashboard-module.gif" server="C:/xampp/htdocs/firmVote0.2/" local="129915281280000000" remote="129915281280000000" Dst="2" /><file name="jquery.wysiwyg.gif" server="C:/xampp/htdocs/firmVote0.2/" local="129915281900000000" remote="129915281900000000" Dst="2" /><file name="Crystal_Clear_user.gif" server="C:/xampp/htdocs/firmVote0.2/" local="129915281280000000" remote="129915281280000000" Dst="2" /><file name="Crystal_Clear_write.gif" server="C:/xampp/htdocs/firmVote0.2/" local="129915281280000000" remote="129915281280000000" Dst="2" /><file name="Crystal_Clear_file.gif" server="C:/xampp/htdocs/firmVote0.2/" local="129915281280000000" remote="129915281280000000" Dst="2" /><file name="Crystal_Clear_files.gif" server="C:/xampp/htdocs/firmVote0.2/" local="129915281280000000" remote="129915281280000000" Dst="2" /><file name="Crystal_Clear_calendar.gif" server="C:/xampp/htdocs/firmVote0.2/" local="129915281280000000" remote="129915281280000000" Dst="2" /><file name="Crystal_Clear_stats.gif" server="C:/xampp/htdocs/firmVote0.2/" local="129915281280000000" remote="129915281280000000" Dst="2" /><file name="Crystal_Clear_settings.gif" server="C:/xampp/htdocs/firmVote0.2/" local="129915281280000000" remote="129915281280000000" Dst="2" /><file name="plus-small.gif" server="C:/xampp/htdocs/firmVote0.2/" local="129915282060000000" remote="129915282060000000" Dst="2" /><file name="tick-circle.gif" server="C:/xampp/htdocs/firmVote0.2/" local="129915282540000000" remote="129915282540000000" Dst="2" /><file name="pencil.gif" server="C:/xampp/htdocs/firmVote0.2/" local="129915282060000000" remote="129915282060000000" Dst="2" /><file name="balloon.gif" server="C:/xampp/htdocs/firmVote0.2/" local="129915281280000000" remote="129915281280000000" Dst="2" /><file name="bin.gif" server="C:/xampp/htdocs/firmVote0.2/" local="129915281280000000" remote="129915281280000000" Dst="2" /><file name="minus-circle.gif" server="C:/xampp/htdocs/firmVote0.2/" local="129915282040000000" remote="129915282040000000" Dst="2" /><file name="arrow-stop-180.gif" server="C:/xampp/htdocs/firmVote0.2/" local="129915281280000000" remote="129915281280000000" Dst="2" /><file name="arrow-180.gif" server="C:/xampp/htdocs/firmVote0.2/" local="129915281280000000" remote="129915281280000000" Dst="2" /><file name="arrow.gif" server="C:/xampp/htdocs/firmVote0.2/" local="129915281280000000" remote="129915281280000000" Dst="2" /><file name="arrow-stop.gif" server="C:/xampp/htdocs/firmVote0.2/" local="129915281280000000" remote="129915281280000000" Dst="2" /><file name="arrow-stop-180-small.gif" server="C:/xampp/htdocs/firmVote0.2/" local="129915281280000000" remote="129915281280000000" Dst="2" /><file name="arrow-180-small.gif" server="C:/xampp/htdocs/firmVote0.2/" local="129915281280000000" remote="129915281280000000" Dst="2" /><file name="arrow-000-small.gif" server="C:/xampp/htdocs/firmVote0.2/" local="129915281280000000" remote="129915281280000000" Dst="2" /><file name="arrow-stop-000-small.gif" server="C:/xampp/htdocs/firmVote0.2/" local="129915281280000000" remote="129915281280000000" Dst="2" /><file name="logo.ico" server="C:/xampp/htdocs/firmVote0.2/" local="130089855319807094" remote="130089855310000000" Dst="2" /><file name="icon-logout.gif" server="Macintosh HD/Applications/XAMPP/xamppfiles/htdocs/firmVote0.2/" local="3429899348" remote="318763443822795860" Dst="-1" /><file name="header-bg.jpg" server="Macintosh HD/Applications/XAMPP/xamppfiles/htdocs/firmVote0.2/" local="3447042062" remote="318763443839938574" Dst="-1" /><file name="logo.gif" server="Macintosh HD/Applications/XAMPP/xamppfiles/htdocs/firmVote0.2/" local="3447356376" remote="318763443840252888" Dst="-1" /><file name="submenu-bg.gif" server="Macintosh HD/Applications/XAMPP/xamppfiles/htdocs/firmVote0.2/" local="3429899426" remote="318763443822795938" Dst="-1" /><file name="tab-left.gif" server="Macintosh HD/Applications/XAMPP/xamppfiles/htdocs/firmVote0.2/" local="3429899444" remote="318763443822795956" Dst="-1" /><file name="tab-right.gif" server="Macintosh HD/Applications/XAMPP/xamppfiles/htdocs/firmVote0.2/" local="3429899444" remote="318763443822795956" Dst="-1" /><file name="tab-active-left.gif" server="Macintosh HD/Applications/XAMPP/xamppfiles/htdocs/firmVote0.2/" local="3429899444" remote="318763443822795956" Dst="-1" /><file name="tab-active-right.gif" server="Macintosh HD/Applications/XAMPP/xamppfiles/htdocs/firmVote0.2/" local="3429899444" remote="318763443822795956" Dst="-1" /><file name="module-body-left-bg.gif" server="Macintosh HD/Applications/XAMPP/xamppfiles/htdocs/firmVote0.2/" local="3429899404" remote="318763443822795916" Dst="-1" /><file name="module-body-right-bg.gif" server="Macintosh HD/Applications/XAMPP/xamppfiles/htdocs/firmVote0.2/" local="3429899404" remote="318763443822795916" Dst="-1" /><file name="module-header-left-bg.gif" server="Macintosh HD/Applications/XAMPP/xamppfiles/htdocs/firmVote0.2/" local="3429899404" remote="318763443822795916" Dst="-1" /><file name="module-header-right-bg.gif" server="Macintosh HD/Applications/XAMPP/xamppfiles/htdocs/firmVote0.2/" local="3429899404" remote="318763443822795916" Dst="-1" /><file name="button-right-bg-m.gif" server="Macintosh HD/Applications/XAMPP/xamppfiles/htdocs/firmVote0.2/" local="3429899328" remote="318763443822795840" Dst="-1" /><file name="button-left-bg-m.gif" server="Macintosh HD/Applications/XAMPP/xamppfiles/htdocs/firmVote0.2/" local="3429899328" remote="318763443822795840" Dst="-1" /><file name="button-right-bg.gif" server="Macintosh HD/Applications/XAMPP/xamppfiles/htdocs/firmVote0.2/" local="3429899328" remote="318763443822795840" Dst="-1" /><file name="button-left-bg.gif" server="Macintosh HD/Applications/XAMPP/xamppfiles/htdocs/firmVote0.2/" local="3429899328" remote="318763443822795840" Dst="-1" /><file name="input-bg.gif" server="Macintosh HD/Applications/XAMPP/xamppfiles/htdocs/firmVote0.2/" local="3429899368" remote="318763443822795880" Dst="-1" /><file name="input-bg-focus.gif" server="Macintosh HD/Applications/XAMPP/xamppfiles/htdocs/firmVote0.2/" local="3429899368" remote="318763443822795880" Dst="-1" /><file name="submit-green-bg.gif" server="Macintosh HD/Applications/XAMPP/xamppfiles/htdocs/firmVote0.2/" local="3429899444" remote="318763443822795956" Dst="-1" /><file name="submit-green-bg-hover.gif" server="Macintosh HD/Applications/XAMPP/xamppfiles/htdocs/firmVote0.2/" local="3429899444" remote="318763443822795956" Dst="-1" /><file name="submit-gray-bg.gif" server="Macintosh HD/Applications/XAMPP/xamppfiles/htdocs/firmVote0.2/" local="3429899444" remote="318763443822795956" Dst="-1" /><file name="submit-gray-bg-hover.gif" server="Macintosh HD/Applications/XAMPP/xamppfiles/htdocs/firmVote0.2/" local="3429899444" remote="318763443822795956" Dst="-1" /><file name="tick-on-white.gif" server="Macintosh HD/Applications/XAMPP/xamppfiles/htdocs/firmVote0.2/" local="3429899454" remote="318763443822795966" Dst="-1" /><file name="cross-on-white.gif" server="Macintosh HD/Applications/XAMPP/xamppfiles/htdocs/firmVote0.2/" local="3429899328" remote="318763443822795840" Dst="-1" /><file name="notification-tick.gif" server="Macintosh HD/Applications/XAMPP/xamppfiles/htdocs/firmVote0.2/" local="3429899406" remote="318763443822795918" Dst="-1" /><file name="notification-information.gif" server="Macintosh HD/Applications/XAMPP/xamppfiles/htdocs/firmVote0.2/" local="3429899404" remote="318763443822795916" Dst="-1" /><file name="notification-exclamation.gif" server="Macintosh HD/Applications/XAMPP/xamppfiles/htdocs/firmVote0.2/" local="3429899404" remote="318763443822795916" Dst="-1" /><file name="notification-slash.gif" server="Macintosh HD/Applications/XAMPP/xamppfiles/htdocs/firmVote0.2/" local="3429899404" remote="318763443822795916" Dst="-1" /><file name="indicator-bg.gif" server="Macintosh HD/Applications/XAMPP/xamppfiles/htdocs/firmVote0.2/" local="3429899366" remote="318763443822795878" Dst="-1" /><file name="indicator-green-to-red.gif" server="Macintosh HD/Applications/XAMPP/xamppfiles/htdocs/firmVote0.2/" local="3429899366" remote="318763443822795878" Dst="-1" /><file name="indicator-red-to-green.gif" server="Macintosh HD/Applications/XAMPP/xamppfiles/htdocs/firmVote0.2/" local="3429899368" remote="318763443822795880" Dst="-1" /><file name="cross-small.gif" server="Macintosh HD/Applications/XAMPP/xamppfiles/htdocs/firmVote0.2/" local="3429899328" remote="318763443822795840" Dst="-1" /><file name="tick-small.gif" server="Macintosh HD/Applications/XAMPP/xamppfiles/htdocs/firmVote0.2/" local="3429899454" remote="318763443822795966" Dst="-1" /><file name="user.gif" server="Macintosh HD/Applications/XAMPP/xamppfiles/htdocs/firmVote0.2/" local="3429899454" remote="318763443822795966" Dst="-1" /><file name="user-female.gif" server="Macintosh HD/Applications/XAMPP/xamppfiles/htdocs/firmVote0.2/" local="3429899454" remote="318763443822795966" Dst="-1" /><file name="arrow-curve-180-left.gif" server="Macintosh HD/Applications/XAMPP/xamppfiles/htdocs/firmVote0.2/" local="3429899328" remote="318763443822795840" Dst="-1" /><file name="arrow-curve-000-left.gif" server="Macintosh HD/Applications/XAMPP/xamppfiles/htdocs/firmVote0.2/" local="3429899328" remote="318763443822795840" Dst="-1" /><file name="Crystal_Project_mail_open.gif" server="Macintosh HD/Applications/XAMPP/xamppfiles/htdocs/firmVote0.2/" local="3429899328" remote="318763443822795840" Dst="-1" /><file name="Crystal_Clear_locked.gif" server="Macintosh HD/Applications/XAMPP/xamppfiles/htdocs/firmVote0.2/" local="3429899328" remote="318763443822795840" Dst="-1" /><file name="dashboard-module.gif" server="Macintosh HD/Applications/XAMPP/xamppfiles/htdocs/firmVote0.2/" local="3429899328" remote="318763443822795840" Dst="-1" /><file name="jquery.wysiwyg.gif" server="Macintosh HD/Applications/XAMPP/xamppfiles/htdocs/firmVote0.2/" local="3429899390" remote="318763443822795902" Dst="-1" /><file name="logo.ico" server="Macintosh HD/Applications/XAMPP/xamppfiles/htdocs/firmVote0.2/" local="3447356731" remote="318763443840253243" Dst="-1" /><file name="pencil.gif" server="Macintosh HD/Applications/XAMPP/xamppfiles/htdocs/firmVote0.2/" local="3429899406" remote="318763443822795918" Dst="-1" /><file name="bin.gif" server="Macintosh HD/Applications/XAMPP/xamppfiles/htdocs/firmVote0.2/" local="3429899328" remote="318763443822795840" Dst="-1" /><file name="arrow-stop-180.gif" server="Macintosh HD/Applications/XAMPP/xamppfiles/htdocs/firmVote0.2/" local="3429899328" remote="318763443822795840" Dst="-1" /><file name="arrow-180.gif" server="Macintosh HD/Applications/XAMPP/xamppfiles/htdocs/firmVote0.2/" local="3429899328" remote="318763443822795840" Dst="-1" /><file name="arrow.gif" server="Macintosh HD/Applications/XAMPP/xamppfiles/htdocs/firmVote0.2/" local="3429899328" remote="318763443822795840" Dst="-1" /><file name="arrow-stop.gif" server="Macintosh HD/Applications/XAMPP/xamppfiles/htdocs/firmVote0.2/" local="3429899328" remote="318763443822795840" Dst="-1" /><file name="Crystal_Clear_user.gif" server="Macintosh HD/Applications/XAMPP/xamppfiles/htdocs/firmVote0.2/" local="3429899328" remote="318763443822795840" Dst="-1" /><file name="Crystal_Clear_write.gif" server="Macintosh HD/Applications/XAMPP/xamppfiles/htdocs/firmVote0.2/" local="3429899328" remote="318763443822795840" Dst="-1" /><file name="Crystal_Clear_calendar.gif" server="Macintosh HD/Applications/XAMPP/xamppfiles/htdocs/firmVote0.2/" local="3429899328" remote="318763443822795840" Dst="-1" /><file name="Crystal_Clear_file.gif" server="Macintosh HD/Applications/XAMPP/xamppfiles/htdocs/firmVote0.2/" local="3429899328" remote="318763443822795840" Dst="-1" /><file name="Crystal_Clear_files.gif" server="Macintosh HD/Applications/XAMPP/xamppfiles/htdocs/firmVote0.2/" local="3429899328" remote="318763443822795840" Dst="-1" /><file name="Crystal_Clear_stats.gif" server="Macintosh HD/Applications/XAMPP/xamppfiles/htdocs/firmVote0.2/" local="3429899328" remote="318763443822795840" Dst="-1" /><file name="Crystal_Clear_settings.gif" server="Macintosh HD/Applications/XAMPP/xamppfiles/htdocs/firmVote0.2/" local="3429899328" remote="318763443822795840" Dst="-1" /><file name="tick-circle.gif" server="Macintosh HD/Applications/XAMPP/xamppfiles/htdocs/firmVote0.2/" local="3429899454" remote="318763443822795966" Dst="-1" /><file name="plus-small.gif" server="Macintosh HD/Applications/XAMPP/xamppfiles/htdocs/firmVote0.2/" local="3429899406" remote="318763443822795918" Dst="-1" /></dwsync>